{
  "version": 2,
  "categories": [
    { "id": "deep", "name": "Deep work", "color": "#9b87f5", "visible": true, "groupId":"work" },
    { "id": "meetings", "name": "Meetings", "color": "#53b8d8", "visible": true, "groupId":"work" },
    { "id": "learning", "name": "Learning", "color": "#dec05a", "visible": true, "groupId":"work" },
    { "id": "health", "name": "Health", "color": "#59c799", "visible": true, "groupId":"life" },
    { "id": "personal", "name": "Personal", "color": "#ef9866", "visible": true, "groupId":"life" }
  ],
  "groups":[{"id":"work","name":"WORK"},{"id":"life","name":"LIFE"}],
  "quoteBank":["Shape the week before it shapes you.","Make time for what matters.","A calm plan makes room for good work.","Protect your attention; spend it deliberately.","Leave space for the unexpected."],
  "currentQuote":"Shape the week before it shapes you.",
  "settings": {
    "wakeHour": 6,
    "sleepHour": 23,
    "snapMinutes": 15,
    "defaultDuration": 1,
    "density": "default",
    "hourScale": 1,
    "defaultCategoryId":"deep",
    "showWeekends": true,
    "timeFormat": "12h",
    "underlayOpacity": 14
  },
  "blocks": [
    { "id":"plan-1", "date":"2026-07-06", "start":7.5, "end":8.5, "title":"Morning run", "categoryId":"health", "layer":"plan" },
    { "id":"plan-2", "date":"2026-07-06", "start":9, "end":11.5, "title":"Product strategy", "categoryId":"deep", "layer":"plan" },
    { "id":"plan-3", "date":"2026-07-06", "start":13, "end":14, "title":"Lunch with Alex", "categoryId":"personal", "layer":"plan" },
    { "id":"plan-4", "date":"2026-07-06", "start":15, "end":16.5, "title":"Design review", "categoryId":"meetings", "layer":"plan" },
    { "id":"plan-5", "date":"2026-07-07", "start":8, "end":9, "title":"Weekly planning", "categoryId":"deep", "layer":"plan" },
    { "id":"plan-6", "date":"2026-07-07", "start":10, "end":11, "title":"Team stand-up", "categoryId":"meetings", "layer":"plan" },
    { "id":"plan-7", "date":"2026-07-07", "start":11.5, "end":14, "title":"Focus: prototype", "categoryId":"deep", "layer":"plan" },
    { "id":"plan-8", "date":"2026-07-07", "start":17.5, "end":19, "title":"Read & notes", "categoryId":"learning", "layer":"plan" },
    { "id":"plan-9", "date":"2026-07-08", "start":7, "end":8, "title":"Gym", "categoryId":"health", "layer":"plan" },
    { "id":"plan-10", "date":"2026-07-08", "start":9, "end":12, "title":"Build dashboard", "categoryId":"deep", "layer":"plan" },
    { "id":"plan-11", "date":"2026-07-08", "start":14, "end":15, "title":"Client sync", "categoryId":"meetings", "layer":"plan" },
    { "id":"plan-12", "date":"2026-07-09", "start":8.5, "end":10.5, "title":"Research sprint", "categoryId":"deep", "layer":"plan" },
    { "id":"plan-13", "date":"2026-07-09", "start":11, "end":12, "title":"Project check-in", "categoryId":"meetings", "layer":"plan" },
    { "id":"plan-14", "date":"2026-07-09", "start":16, "end":17.5, "title":"Course module", "categoryId":"learning", "layer":"plan" },
    { "id":"plan-15", "date":"2026-07-10", "start":7.5, "end":8.5, "title":"Morning run", "categoryId":"health", "layer":"plan" },
    { "id":"plan-16", "date":"2026-07-10", "start":9, "end":12, "title":"Finish proposal", "categoryId":"deep", "layer":"plan" },
    { "id":"plan-17", "date":"2026-07-10", "start":14, "end":15, "title":"Weekly review", "categoryId":"personal", "layer":"plan" },
    { "id":"plan-18", "date":"2026-07-11", "start":9, "end":10.5, "title":"Long walk", "categoryId":"health", "layer":"plan" },
    { "id":"plan-19", "date":"2026-07-11", "start":12, "end":14, "title":"Family lunch", "categoryId":"personal", "layer":"plan" },
    { "id":"plan-20", "date":"2026-07-12", "start":9.5, "end":11, "title":"Weekly reset", "categoryId":"personal", "layer":"plan" },
    { "id":"plan-21", "date":"2026-07-12", "start":16, "end":18, "title":"Learn TypeScript", "categoryId":"learning", "layer":"plan" },
    { "id":"actual-1", "date":"2026-07-06", "start":7.5, "end":8.25, "title":"Morning run", "categoryId":"health", "layer":"actual", "status":"completed" },
    { "id":"actual-2", "date":"2026-07-06", "start":9.25, "end":11.25, "title":"Product strategy", "categoryId":"deep", "layer":"actual", "status":"partial" },
    { "id":"actual-3", "date":"2026-07-06", "start":15.25, "end":16.75, "title":"Design review", "categoryId":"meetings", "layer":"actual", "status":"completed" },
    { "id":"actual-4", "date":"2026-07-07", "start":8, "end":9.25, "title":"Weekly planning", "categoryId":"deep", "layer":"actual", "status":"completed" },
    { "id":"actual-5", "date":"2026-07-07", "start":10.25, "end":11, "title":"Team stand-up", "categoryId":"meetings", "layer":"actual", "status":"completed" },
    { "id":"actual-6", "date":"2026-07-07", "start":12, "end":14, "title":"Focus: prototype", "categoryId":"deep", "layer":"actual", "status":"partial" },
    { "id":"actual-7", "date":"2026-07-08", "start":7.25, "end":8, "title":"Gym", "categoryId":"health", "layer":"actual", "status":"completed" },
    { "id":"actual-8", "date":"2026-07-08", "start":9, "end":11.5, "title":"Build dashboard", "categoryId":"deep", "layer":"actual", "status":"partial" },
    { "id":"actual-9", "date":"2026-07-08", "start":14.25, "end":15.25, "title":"Client sync", "categoryId":"meetings", "layer":"actual", "status":"completed" },
    { "id":"actual-10", "date":"2026-07-09", "start":9, "end":10.5, "title":"Research sprint", "categoryId":"deep", "layer":"actual", "status":"partial" },
    { "id":"actual-11", "date":"2026-07-09", "start":11, "end":12, "title":"Project check-in", "categoryId":"meetings", "layer":"actual", "status":"completed" },
    { "id":"actual-12", "date":"2026-07-10", "start":7.5, "end":8.25, "title":"Morning run", "categoryId":"health", "layer":"actual", "status":"completed" }
  ]
}
